xlai_base/__init__.py
xlai_base/Department/DepartmentPart.py
xlai_base/Department/__init__.py
xlai_base/Util/JSONUtil.py
xlai_base/Util/XLLogger.py
xlai_base/Util/XLRedisUtil.py
xlai_base/Util/XLStorageUtil.py
xlai_base/Util/XLTools.py
xlai_base/Util/__init__.py
xlai_base/XLSYS/__init__.py
xlai_base/XLSYS/Base/BaseClass.py
xlai_base/XLSYS/Base/SYSBaseEntity.py
xlai_base/XLSYS/Base/XLObjectUtil.py
xlai_base/XLSYS/Base/__init__.py
xlai_base/XLSYS/Entities/RunEntiy.py
xlai_base/XLSYS/Entities/Storage.py
xlai_base/XLSYS/Entities/XLDataMark.py
xlai_base/XLSYS/Entities/XLDataStructure.py
xlai_base/XLSYS/Entities/XLExceptionEntities.py
xlai_base/XLSYS/Entities/__init__.py
xlai_base/XLSYS/Link/MqHttp.py
xlai_base/XLSYS/Link/MqMessage.py
xlai_base/XLSYS/Link/XLHttp.py
xlai_base/XLSYS/Link/XLLinkEntity.py
xlai_base/XLSYS/Link/__init__.py
xlai_base-1.0.15.dist-info/licenses/LICENSE
xlai_base-1.0.15.dist-info/METADATA
xlai_base-1.0.15.dist-info/WHEEL
xlai_base-1.0.15.dist-info/top_level.txt
xlai_base-1.0.15.dist-info/RECORD
