Metadata-Version: 2.4
Name: xlai_base
Version: 1.0.15
Summary: xlai common tool package
Home-page: 
Author: 星海
Author-email: cool.xinglin.he@gmail.com
Classifier: Programming Language :: Python :: 3
Classifier: License :: OSI Approved :: MIT License
Classifier: Operating System :: OS Independent
Requires-Python: >=3.9
License-File: LICENSE
Requires-Dist: python-logstash>=0.4.8
Dynamic: author
Dynamic: author-email
Dynamic: classifier
Dynamic: description
Dynamic: description-content-type
Dynamic: license-file
Dynamic: requires-dist
Dynamic: requires-python
Dynamic: summary
